{
    "name": "MemeticSwap List",
    "timestamp": "2022-12-15T19:01:09+00:00",
    "logoURI": "https://memeticswap.com/favicon.ico",
    "version": {
        "major": 2,
        "minor": 0,
        "patch": 0
    },
    "tokens": [
        {
            "name": "Memetic",
            "address": "0xE5Ca307249662fe2Dc4c91c91aab44ea8578E671",
            "symbol": "MEMETIC",
            "decimals": 18,
            "chainId": 18159,
            "logoURI": "https://raw.githubusercontent.com/MemeticSwap/tokenlist/master/logos/memetic.png"
        },
        {
            "name": "Pom USD Ethereum-bridged",
            "address": "0x27d789b89a441ccb6fcdb92650f1e667c965df7a",
            "symbol": "PUSDe",
            "decimals": 6,
            "chainId": 18159,
            "logoURI": "https://raw.githubusercontent.com/Prism-Network-io/default-token-list/master/logos/pom/0x27d789b89a441ccb6fcdb92650f1e667c965df7a/logo.png"
        },
        {
            "name": "Wrapped POM",
            "address": "0xC84D8d03aA41EF941721A4D77b24bB44D7C7Ac55",
            "symbol": "WPOM",
            "decimals": 18,
            "chainId": 18159,
            "logoURI": "https://raw.githubusercontent.com/Prism-Network-io/default-token-list/master/logos/pom/0xC84D8d03aA41EF941721A4D77b24bB44D7C7Ac55/logo.png"
        },
        {
            "name": "TetherUSD BSC-bridged",
            "address": "0x326d041519E24fE843ce313CFB8D0F07F653B2C7",
            "symbol": "USDT",
            "decimals": 18,
            "chainId": 18159,
            "logoURI": "https://raw.githubusercontent.com/MemeticSwap/tokenlist/master/logos/usdt.webp"
        },
        {
            "name": "POM GOVERNANCE",
            "address": "0x8BB07ad76ADdE952e83f2876c9bDeA9cc5B3a51E",
            "symbol": "POMG",
            "decimals": 18,
            "chainId": 18159,
            "logoURI": "https://raw.githubusercontent.com/Prism-Network-io/default-token-list/master/logos/pom/0xC84D8d03aA41EF941721A4D77b24bB44D7C7Ac55/logo.png"
        },
        {
            "name": "Pomeranian",
            "address": "0x58843CB63012e7C2Ad643857977efD32147a3C23",
            "symbol": "POMD",
            "decimals": 18,
            "chainId": 18159,
            "logoURI": "https://raw.githubusercontent.com/MemeticSwap/tokenlist/master/logos/pomd.jpg"
        },
        {
            "name": "POMzi Coin",
            "address": "0x9b63aEc23bEeA0291Eb57fdcd9d8e92fF9D7C5E5",
            "symbol": "POMZI",
            "decimals": 18,
            "chainId": 18159,
            "logoURI": "https://raw.githubusercontent.com/MemeticSwap/tokenlist/master/logos/pomzi.png"
        },
        {
            "name": "POM Build",
            "address": "0x091FA2d92e2b2358bE97b2a0bAaB8398EEC144Cf",
            "symbol": "PBUILD",
            "decimals": 18,
            "chainId": 18159,
            "logoURI": "https://raw.githubusercontent.com/MemeticSwap/tokenlist/master/logos/pbuild.jpg"
        },
        {
            "name": "Meme Shib",
            "address": "0x71993AE0419422810600248019619c2f9F073030",
            "symbol": "MS",
            "decimals": 9,
            "chainId": 18159,
            "logoURI": "https://raw.githubusercontent.com/MemeticSwap/tokenlist/master/logos/memeshib.jpg"
        },
        {
            "name": "GreenRanger",
            "address": "0xFBe503022720F6623C4095e5ad3C08c3925aCb10",
            "symbol": "GreenRanger",
            "decimals": 18,
            "chainId": 18159,
            "logoURI": "https://raw.githubusercontent.com/MemeticSwap/tokenlist/master/logos/greenranger.jpg"
        },
        {
            "name": "FLOKI ON POMCHAIN",
            "address": "0x3B13A9BB49316dbbe009947142f995bFa005aE36",
            "symbol": "POMF",
            "decimals": 9,
            "chainId": 18159,
            "logoURI": "https://raw.githubusercontent.com/MemeticSwap/tokenlist/master/logos/pomfloki.jpg"
        }
    ]
}
